{
  "title": "Friday Sermon 15 December 1995",
  "url": "https://www.youtube.com/watch?v=p8Psx4BtsfU",
  "description": "O People! A manifest proof has indeed come to you from your Lord and We have sent down to you a clear light.\n\nSo as for those who believe in Allah and hold fast to Him will He surely admit to His mercy and grace and will guide them on a straight path to Himself.\n\n('The Holy Quran'.  al-Nisa [The Women]: 175, 176).\n\n\nThe Community in New Zealand is holding its seventh Jalsa Salana from 17 December.  I send greetings of Assalamo Alaikum to their President and the entire Community and request the Community to remember them in your prayers.\n\n'The Holy Quran' and the Holy Prophet \ufdfa are manifest proofs and light and they are the light that is created but the light of Allah the Almighty is uncreated.\n\nHere both 'The Holy Quran' and Muhammad the Holy Prophet of Allah have been called light.  There are many other verses in 'The Holy Quran' where 'The Holy Quran' and Muhammad the Messenger of Allah are mentioned together through a single pronoun.  \n\nThere is no difference between the light of Muhammad the Chosen Prophet and the light of the Quran.  Muhammad the Messenger of Allah was the commentary of the Quran in practical terms.  Muhammad the Messenger of Allah was a manifest proof just as 'The Holy Quran' is a manifest proof.  The Promised Messiah (peace be upon him) states:\n\nIf proof is demanded from the lover then know\nMuhammad is a clear proof of Muhammad\n\n(Hazrat Mirza Ghulam Ahmad.  'Durr e Samin Farsi').\n\nWhen Hazrat Abu Bakr Siddique demanded no proof from the Messenger of Allah for what he claimed but asked only to know if he had made the claim and affirmed his truth straightaway it was because the very existence of Allah's Messenger was in itself a clear and open proof. \n\n\nThe text https://www.alislam.org/urdu/pdf/Khutbat-e-Tahir-Vol-14-1995.pdf#page=939\n\n\n\u00a9 The Tahir Archive / MTA International, 2015.",
  "duration": 3942,
  "links_in_desc": [
    "https://www.alislam.org/urdu/pdf/Khutbat-e-Tahir-Vol-14-1995.pdf#page=939\n\n\n\u00a9"
  ]
}